{"name":"Should see information related to Insurance Project","id":"login-to-guru99-website-and-navigate-to-different-projects;should-see-information-related-to-insurance-project","testSteps":[{"number":1,"description":"Close browser","duration":9,"startTime":"2018-07-28T14:46:07.980-04:00[America/New_York]","result":"SUCCESS","precondition":false},{"number":2,"description":"Given I navigate to the login page","duration":6926,"startTime":"2018-07-28T14:46:07.995-04:00[America/New_York]","screenshots":[{"screenshot":"87da6098ccef8303267510aa91f5ae6aefc3028b63d84b1e9f91725838108bb5.png"}],"result":"SUCCESS","precondition":false,"children":[{"number":3,"description":"Open","duration":6342,"startTime":"2018-07-28T14:46:08.213-04:00[America/New_York]","screenshots":[{"screenshot":"87da6098ccef8303267510aa91f5ae6aefc3028b63d84b1e9f91725838108bb5.png"}],"result":"SUCCESS","precondition":false}]},{"number":4,"description":"When I submit username \u0027mgr123\u0027 and password \u0027mgr!23\u0027","duration":2380,"startTime":"2018-07-28T14:46:14.922-04:00[America/New_York]","screenshots":[{"screenshot":"1c0bfd4870c644497a31b472659ae8f2ecbad3bef213dc6ad9de17233a8b9c2c.png"}],"result":"SUCCESS","precondition":false,"children":[{"number":5,"description":"Submit unameand pass: mgr123, mgr!23","duration":1992,"startTime":"2018-07-28T14:46:14.934-04:00[America/New_York]","screenshots":[{"screenshot":"34727814edf650788d29bd3f568feaf8b5837bae79fc5ce6f62e2cb484b4fc09.png"}],"result":"SUCCESS","precondition":false}]},{"number":6,"description":"Then I should be logged in","duration":835,"startTime":"2018-07-28T14:46:17.302-04:00[America/New_York]","screenshots":[{"screenshot":"41cdb26f1017117ea2ee0f87875a6f2c5d17b62cd3fd63b3dd2328f31c734680.png"}],"result":"SUCCESS","precondition":false,"children":[{"number":7,"description":"Loginto guru99 accnt","duration":460,"startTime":"2018-07-28T14:46:17.304-04:00[America/New_York]","screenshots":[{"screenshot":"2f7fd206532b1cad199ae2908bfa9b944b327c55a8745cc5f567453a4c1e8d6e.png"}],"result":"SUCCESS","precondition":false}]},{"number":8,"description":"Given User is already on the home page","duration":876,"startTime":"2018-07-28T14:46:18.137-04:00[America/New_York]","screenshots":[{"screenshot":"ad6081d344696ceab511f92ba9dc2ea391fe3c4b239b80b5e08a1939c0119976.png"}],"result":"SUCCESS","precondition":false,"children":[{"number":9,"description":"User is on home page","duration":484,"startTime":"2018-07-28T14:46:18.139-04:00[America/New_York]","screenshots":[{"screenshot":"e512d2a2d823eb12115d87eadb7517de8260f7fa6f5c556d458ca9a825da0306.png"}],"result":"SUCCESS","precondition":false}]},{"number":10,"description":"When User clicks on Insurance Project link","duration":1185,"startTime":"2018-07-28T14:46:19.014-04:00[America/New_York]","screenshots":[{"screenshot":"5d13d3af45f8060851c50d45ead1fc77d209c8b1c04c787f0bd4b8a2dc7f9a1b.png"}],"result":"SUCCESS","precondition":false},{"number":11,"description":"Then Login page for Insurance gets displayed","duration":439,"startTime":"2018-07-28T14:46:20.200-04:00[America/New_York]","screenshots":[{"screenshot":"5d13d3af45f8060851c50d45ead1fc77d209c8b1c04c787f0bd4b8a2dc7f9a1b.png"}],"result":"SUCCESS","precondition":false},{"number":12,"description":"Then complete registration if you are a new user","duration":1162,"startTime":"2018-07-28T14:46:20.639-04:00[America/New_York]","screenshots":[{"screenshot":"7f6836c6346ae3a35bc600928093060f0b55c261ddf743edaecfb633d653c290.png"}],"result":"SUCCESS","precondition":false},{"number":13,"description":"And enter the login credentials to login to Insurance website","duration":331,"startTime":"2018-07-28T14:46:21.802-04:00[America/New_York]","screenshots":[{"screenshot":"7f6836c6346ae3a35bc600928093060f0b55c261ddf743edaecfb633d653c290.png"}],"result":"SUCCESS","precondition":false}],"userStory":{"id":"login-to-guru99-website-and-navigate-to-different-projects","storyName":"Login to Guru99 website and navigate to different projects","path":"src/test/resources/features/guru99_Login/Login_Guru99.feature","narrative":"  In order to explore different projects in Guru99 \n  I want to login to Guru99 website","type":"feature"},"featureTag":{"name":"Guru99  login/Login to Guru99 website and navigate to different projects","type":"feature"},"title":"Should see information related to Insurance Project","backgroundTitle":"User is Logged In","backgroundDescription":"","tags":[{"name":"Guru99 login/Login to guru99 website and navigate to different projects","type":"feature"},{"name":"Guru99 login","type":"feature"}],"startTime":"2018-07-28T14:46:06.410-04:00[America/New_York]","duration":15859,"projectKey":"","sessionId":"435489e084e38dedbf9cae11c7b6c109","driver":"chrome","manual":false,"testSource":"Cucumber","result":"SUCCESS"}